proxyValidator/__init__.py
proxyValidator/proxyValidator.py
proxyValidator-0.5.dist-info/METADATA
proxyValidator-0.5.dist-info/WHEEL
proxyValidator-0.5.dist-info/top_level.txt
proxyValidator-0.5.dist-info/RECORD
