Metadata-Version: 2.1
Name: proxyValidator
Version: 0.5
Summary: Returns validated proxies
Home-page: https://github.com/zbagdzevicius/proxyValidator
Author: Zygimantas Bagdzevicius
Author-email: zbagdzevicius@gmail.com
License: UNKNOWN
Platform: UNKNOWN
Classifier: Programming Language :: Python :: 3
Classifier: License :: OSI Approved :: MIT License
Classifier: Operating System :: OS Independent
Requires-Dist: requests
